<row>
  <user_id>991</user_id>
  <user_grou_id>1</user_grou_id>
  <user_fname>TESTIMIE</user_fname>
  <user_lname>TESTNAZWISKO</user_lname>
  <user_active>1</user_active>
  <user_login>TESTLOGIN</user_login>
  <user_password>dfs</user_password>
</row>
<row>
  <user_id>992</user_id>
  <user_grou_id>1</user_grou_id>
  <user_fname>TESTIMIE</user_fname>
  <user_lname>TESTNAZWISKO</user_lname>
  <user_active>1</user_active>
  <user_login>TESTLOGIN</user_login>
  <user_password>dfs</user_password>
</row>
<row>
  <user_id>993</user_id>
  <user_grou_id>1</user_grou_id>
  <user_fname>TESTIMIE</user_fname>
  <user_lname>TESTNAZWISKO</user_lname>
  <user_active>1</user_active>
  <user_login>TESTLOGIN</user_login>
  <user_password>dfs</user_password>
</row>
<row>
  <user_id>994</user_id>
  <user_grou_id>1</user_grou_id>
  <user_fname>TESTIMIE</user_fname>
  <user_lname>TESTNAZWISKO</user_lname>
  <user_active>1</user_active>
  <user_login>TESTLOGIN</user_login>
  <user_password>dfs</user_password>
</row>
<row>
  <user_id>995</user_id>
  <user_grou_id>1</user_grou_id>
  <user_fname>TESTIMIE</user_fname>
  <user_lname>TESTNAZWISKO</user_lname>
  <user_active>1</user_active>
  <user_login>TESTLOGIN</user_login>
  <user_password>dfs</user_password>
</row>
<row>
  <user_id>996</user_id>
  <user_grou_id>1</user_grou_id>
  <user_fname>TESTIMIE</user_fname>
  <user_lname>TESTNAZWISKO</user_lname>
  <user_active>1</user_active>
  <user_login>TESTLOGIN</user_login>
  <user_password>dfs</user_password>
</row>
<row>
  <user_id>997</user_id>
  <user_grou_id>1</user_grou_id>
  <user_fname>TESTIMIE</user_fname>
  <user_lname>TESTNAZWISKO</user_lname>
  <user_active>1</user_active>
  <user_login>TESTLOGIN</user_login>
  <user_password>dfs</user_password>
</row>
<row>
  <user_id>998</user_id>
  <user_grou_id>1</user_grou_id>
  <user_fname>TESTIMIE</user_fname>
  <user_lname>TESTNAZWISKO</user_lname>
  <user_active>1</user_active>
  <user_login>TESTLOGIN</user_login>
  <user_password>dfs</user_password>
</row>
<row>
  <user_id>999</user_id>
  <user_grou_id>1</user_grou_id>
  <user_fname>TESTIMIE</user_fname>
  <user_lname>TESTNAZWISKO</user_lname>
  <user_active>1</user_active>
  <user_login>TESTLOGIN</user_login>
  <user_password>dfs</user_password>
</row>
<row>
  <user_id>1000</user_id>
  <user_grou_id>1</user_grou_id>
  <user_fname>TESTIMIE</user_fname>
  <user_lname>TESTNAZWISKO</user_lname>
  <user_active>1</user_active>
  <user_login>TESTLOGIN</user_login>
  <user_password>dfs</user_password>
</row>